barbouse/barbouse.py
barbouse/weather.json
barbouse-0.1.3.dist-info/entry_points.txt
barbouse-0.1.3.dist-info/LICENSE
barbouse-0.1.3.dist-info/WHEEL
barbouse-0.1.3.dist-info/METADATA
barbouse-0.1.3.dist-info/RECORD
